manati/__init__.py
manati/__main__.py
manati/add.py
manati/create.py
manati/deploy.py
manati/manati.py
manati/run.py
manati/utils.py
manati/validators.py
manati/templates/.gitignore
manati/templates/README.md
manati/templates/check.yml
manati/templates/manati.txt
manati/templates/setup.py
manati/templates/source.py
manati/templates/test.py
manati/templates/licenses/Apache
manati/templates/licenses/GPLv3
manati/templates/licenses/MIT
manati-0.3.3.dist-info/LICENSE
manati-0.3.3.dist-info/METADATA
manati-0.3.3.dist-info/WHEEL
manati-0.3.3.dist-info/entry_points.txt
manati-0.3.3.dist-info/top_level.txt
manati-0.3.3.dist-info/RECORD
