Metadata-Version: 2.1
Name: manati
Version: 0.3.3
Summary: A CLI for managing Python projects.
Home-page: https://github.com/maroba/manati
Author: Matthias Baer
Author-email: matthias.r.baer@googlemail.com
License: GPL v3
Keywords: CLI,cli,Python project management
Platform: ALL
Classifier: Operating System :: OS Independent
Classifier: Programming Language :: Python :: 3
Classifier: Intended Audience :: Developers
Classifier: Environment :: Console
Requires-Python: >=3.6
Requires-Dist: Click
Requires-Dist: sphinx
